README.md
setup.cfg
setup.py
skippy/__init__.py
skippy/skippy.py
skippylib/__init__.py
skippylib/abstracts.py
skippylib/attributes.py
skippylib/builder.py
skippylib/communications.py
skippylib/dataformat.py
skippylib/features.py
skippylib/identify.py
skippylib/monitor.py
skippylib/skippy.py
skippylib/statemanager.py
skippylib/version.py
skippylib/watchdog.py
skippylib.egg-info/PKG-INFO
skippylib.egg-info/SOURCES.txt
skippylib.egg-info/dependency_links.txt
skippylib.egg-info/entry_points.txt
skippylib.egg-info/top_level.txt
skippylib/instructions/__init__.py
skippylib/instructions/electrometer/__init__.py
skippylib/instructions/electrometer/albaEm.py
skippylib/instructions/fakeinstruments/__init__.py
skippylib/instructions/fakeinstruments/tester.py
skippylib/instructions/generators/__init__.py
skippylib/instructions/generators/function/__init__.py
skippylib/instructions/generators/function/tektronicsAFG.py
skippylib/instructions/generators/rf/__init__.py
skippylib/instructions/generators/rf/keysightSignalGenerator.py
skippylib/instructions/generators/rf/rohdeSchwarzRFG.py
skippylib/instructions/multimeter/__init__.py
skippylib/instructions/multimeter/keithley2000.py
skippylib/instructions/photomultiplier/__init__.py
skippylib/instructions/photomultiplier/music.py
skippylib/instructions/pumpController/__init__.py
skippylib/instructions/pumpController/norhof900.py
skippylib/instructions/scope/__init__.py
skippylib/instructions/scope/agilentDSO.py
skippylib/instructions/scope/tektronixDPO.py
skippylib/instructions/sourcemeter/__init__.py
skippylib/instructions/sourcemeter/keithley26XX.py
skippylib/instructions/spectrumAnalyser/__init__.py
skippylib/instructions/spectrumAnalyser/rohdeSchwarzFSP.py
skippylib/instructions/temperatureController/__init__.py
skippylib/instructions/temperatureController/arroyo5300.py
tester/__init__.py
tester/fakeInstrument.py
tester/instrIdn.py
tester/restarter.py
tester/instrAttrs/__init__.py
tester/instrAttrs/fakeBoolean.py
tester/instrAttrs/fakeNumber.py
tester/instrAttrs/fakeString.py