Metadata-Version: 1.1
Name: skippylib
Version: 1.5.0
Summary: Python module and a Tango Device Server to gain control to instruments that support the scpi protocol. Brother project of the scpilib.
Home-page: https://github.com/srgblnch/skippy
Author: Sergi Blanch-Torne
Author-email: sblanch@cells.es
License: GPLv3+
Platform: UNKNOWN
Classifier: Development Status :: 5 - Production/Stable
Classifier: Intended Audience :: Developers
Classifier: Intended Audience :: Science/Research
Classifier: License :: OSI Approved :: GNU General Public License v3 or later (GPLv3+)
Classifier: Operating System :: POSIX
Classifier: Programming Language :: Python :: 2.6
Classifier: Programming Language :: Python :: 2.7
Classifier: Topic :: Scientific/Engineering :: Interface Engine/Protocol Translator
Classifier: Topic :: Software Development :: Embedded Systems
Classifier: Topic :: Software Development :: Libraries :: Python Modules
